netQuil/__init__.py
netQuil/agents.py
netQuil/clock.py
netQuil/connections.py
netQuil/devices.py
netQuil/distributedGates.py
netQuil/noise.py
netQuil/simulator.py
netQuil-1.0.2.dist-info/LICENSE
netQuil-1.0.2.dist-info/METADATA
netQuil-1.0.2.dist-info/WHEEL
netQuil-1.0.2.dist-info/top_level.txt
netQuil-1.0.2.dist-info/RECORD
