Metadata-Version: 2.1
Name: netQuil
Version: 1.0.2
Summary: A Distributed Quantum Network Simulator
Home-page: https://github.com/att-innovate/netQuil
Author: Zac Espinosa, Matt Radzihovsky
Author-email: zespinosa97@gmail.com, mattradz@stanford.edu
License: MIT
Platform: UNKNOWN
Classifier: Programming Language :: Python :: 3
Classifier: License :: OSI Approved :: MIT License
Classifier: Operating System :: OS Independent
Requires-Dist: numpy
Requires-Dist: pyquil
